LICENSE.txt
MANIFEST.in
README.md
setup.cfg
setup.py
spotinst_sdk2/__init__.py
spotinst_sdk2/client.py
spotinst_sdk2/session.py
spotinst_sdk2/version.py
spotinst_sdk2/clients/__init__.py
spotinst_sdk2/clients/admin/__init__.py
spotinst_sdk2/clients/elastigroup/__init__.py
spotinst_sdk2/clients/functions/__init__.py
spotinst_sdk2/clients/mcs/__init__.py
spotinst_sdk2/clients/mlb/__init__.py
spotinst_sdk2/clients/mrscaler/__init__.py
spotinst_sdk2/clients/ocean/__init__.py
spotinst_sdk2/clients/subscription/__init__.py
spotinst_sdk2/models/__init__.py
spotinst_sdk2/models/admin/__init__.py
spotinst_sdk2/models/admin/user_mapping.py
spotinst_sdk2/models/elastigroup/__init__.py
spotinst_sdk2/models/elastigroup/aws/__init__.py
spotinst_sdk2/models/elastigroup/aws/asg.py
spotinst_sdk2/models/elastigroup/aws/deployment.py
spotinst_sdk2/models/elastigroup/aws/deployment_action.py
spotinst_sdk2/models/elastigroup/aws/stateful.py
spotinst_sdk2/models/elastigroup/azure/__init__.py
spotinst_sdk2/models/elastigroup/azure/task.py
spotinst_sdk2/models/elastigroup/gcp/__init__.py
spotinst_sdk2/models/elastigroup/gcp/gke.py
spotinst_sdk2/models/functions/__init__.py
spotinst_sdk2/models/mlb/__init__.py
spotinst_sdk2/models/mrscaler/__init__.py
spotinst_sdk2/models/mrscaler/aws/__init__.py
spotinst_sdk2/models/ocean/__init__.py
spotinst_sdk2/models/ocean/aws/__init__.py
spotinst_sdk2/models/subscription/__init__.py
spotinst_sdk_beta2.egg-info/PKG-INFO
spotinst_sdk_beta2.egg-info/SOURCES.txt
spotinst_sdk_beta2.egg-info/dependency_links.txt
spotinst_sdk_beta2.egg-info/requires.txt
spotinst_sdk_beta2.egg-info/top_level.txt