Metadata-Version: 1.1
Name: spotinst-sdk-beta2
Version: 2.1.2
Summary: A Python SDK for Spotinst
Home-page: https://github.com/spotinst/spotinst-sdk-beta-python
Author: Spotinst
Author-email: service@spotinst.com
License: MIT
Keywords: spotinst spot instances aws ec2 cloud infrastructure development elastigroup
Platform: UNKNOWN
Classifier: Development Status :: 3 - Alpha
Classifier: Intended Audience :: Developers
Classifier: Topic :: Software Development :: Libraries :: Python Modules
Classifier: License :: OSI Approved :: MIT License
Classifier: Programming Language :: Python :: 2.7
Classifier: Programming Language :: Python :: 3.6
